Metadata-Version: 2.1
Name: parsr
Version: 0.4.2
Summary: Parsr is a simple parser combinator library in pure python.
Home-page: https://parsr.readthedocs.io/en/latest/parsr.html
License: Apache 2.0
Platform: UNKNOWN
Classifier: Intended Audience :: Developers
Classifier: Natural Language :: English
Classifier: License :: OSI Approved :: Apache Software License
Classifier: Programming Language :: Python
Classifier: Programming Language :: Python :: 3.6
Classifier: Programming Language :: Python :: 3.7
Requires-Dist: six (==1.15.0)
Provides-Extra: develop
Requires-Dist: twine (==3.2.0) ; extra == 'develop'
Requires-Dist: sphinx-rtd-theme (==0.5.0) ; extra == 'develop'
Requires-Dist: wheel (==0.35.1) ; extra == 'develop'
Requires-Dist: pytest-cov (==2.10.1) ; extra == 'develop'
Requires-Dist: coverage (==5.2.1) ; extra == 'develop'
Requires-Dist: sphinx (==3.2.1) ; extra == 'develop'
Requires-Dist: setuptools (==50.3.0) ; extra == 'develop'
Requires-Dist: pytest (==6.0.1) ; extra == 'develop'
Requires-Dist: ipython (==7.17.0) ; extra == 'develop'
Provides-Extra: docs
Requires-Dist: sphinx (==3.2.1) ; extra == 'docs'
Requires-Dist: sphinx-rtd-theme (==0.5.0) ; extra == 'docs'
Requires-Dist: six (==1.15.0) ; extra == 'docs'
Provides-Extra: testing
Requires-Dist: coverage (==5.2.1) ; extra == 'testing'
Requires-Dist: pytest-cov (==2.10.1) ; extra == 'testing'
Requires-Dist: pytest (==6.0.1) ; extra == 'testing'
Requires-Dist: six (==1.15.0) ; extra == 'testing'
